ask_smapi_sdk/__init__.py
ask_smapi_sdk/__version__.py
ask_smapi_sdk/smapi_builder.py
ask_smapi_sdk/utils.py
ask_smapi_sdk-1.0.0.dist-info/LICENSE
ask_smapi_sdk-1.0.0.dist-info/METADATA
ask_smapi_sdk-1.0.0.dist-info/NOTICE.txt
ask_smapi_sdk-1.0.0.dist-info/WHEEL
ask_smapi_sdk-1.0.0.dist-info/top_level.txt
ask_smapi_sdk-1.0.0.dist-info/RECORD
